CHANGELOG.txt
LICENCE.txt
MANIFEST.in
README.txt
setup.py
.eggs/README.txt
.eggs/torch-1.9.0-py3.8-win-amd64.egg/EGG-INFO/entry_points.txt
.eggs/torch-1.9.0-py3.8-win-amd64.egg/EGG-INFO/requires.txt
.eggs/torch-1.9.0-py3.8-win-amd64.egg/EGG-INFO/top_level.txt
.eggs/torch-1.9.0-py3.8-win-amd64.egg/caffe2/__init__.py
.eggs/torch-1.9.0-py3.8-win-amd64.egg/caffe2/contrib/__init__.py
.eggs/torch-1.9.0-py3.8-win-amd64.egg/caffe2/contrib/aten/__init__.py
.eggs/torch-1.9.0-py3.8-win-amd64.egg/caffe2/contrib/aten/aten_test.py
.eggs/torch-1.9.0-py3.8-win-amd64.egg/caffe2/contrib/aten/gen_op.py
.eggs/torch-1.9.0-py3.8-win-amd64.egg/caffe2/contrib/aten/docs/__init__.py
.eggs/torch-1.9.0-py3.8-win-amd64.egg/caffe2/contrib/aten/docs/sample.py
.eggs/torch-1.9.0-py3.8-win-amd64.egg/caffe2/contrib/gloo/__init__.py
.eggs/torch-1.9.0-py3.8-win-amd64.egg/caffe2/contrib/gloo/gloo_test.py
.eggs/torch-1.9.0-py3.8-win-amd64.egg/caffe2/contrib/nccl/__init__.py
.eggs/torch-1.9.0-py3.8-win-amd64.egg/caffe2/contrib/nccl/nccl_ops_test.py
.eggs/torch-1.9.0-py3.8-win-amd64.egg/caffe2/contrib/nnpack/__init__.py
.eggs/torch-1.9.0-py3.8-win-amd64.egg/caffe2/contrib/nnpack/nnpack_ops_test.py
.eggs/torch-1.9.0-py3.8-win-amd64.egg/caffe2/contrib/playground/AnyExp.py
.eggs/torch-1.9.0-py3.8-win-amd64.egg/caffe2/contrib/playground/AnyExpOnTerm.py
.eggs/torch-1.9.0-py3.8-win-amd64.egg/caffe2/contrib/playground/ModuleRegister.py
.eggs/torch-1.9.0-py3.8-win-amd64.egg/caffe2/contrib/playground/__init__.py
.eggs/torch-1.9.0-py3.8-win-amd64.egg/caffe2/contrib/playground/checkpoint.py
.eggs/torch-1.9.0-py3.8-win-amd64.egg/caffe2/contrib/playground/compute_loss.py
.eggs/torch-1.9.0-py3.8-win-amd64.egg/caffe2/contrib/playground/compute_topk_accuracy.py
.eggs/torch-1.9.0-py3.8-win-amd64.egg/caffe2/contrib/playground/meter.py
.eggs/torch-1.9.0-py3.8-win-amd64.egg/caffe2/contrib/playground/module_map.py
.eggs/torch-1.9.0-py3.8-win-amd64.egg/caffe2/contrib/playground/output_generator.py
.eggs/torch-1.9.0-py3.8-win-amd64.egg/caffe2/contrib/playground/resnetdemo/IN1k_resnet.py
.eggs/torch-1.9.0-py3.8-win-amd64.egg/caffe2/contrib/playground/resnetdemo/IN1k_resnet_no_test_model.py
SparseCOOTensorMulPyTorch.egg-info/PKG-INFO
SparseCOOTensorMulPyTorch.egg-info/SOURCES.txt
SparseCOOTensorMulPyTorch.egg-info/dependency_links.txt
SparseCOOTensorMulPyTorch.egg-info/requires.txt
SparseCOOTensorMulPyTorch.egg-info/top_level.txt